formation/__init__.py
formation/__main__.py
formation/loader.py
formation/meth.py
formation/preprocessors.py
formation/themes.py
formation/utils.py
formation/formats/__init__.py
formation/formats/_base.py
formation/formats/_json.py
formation/formats/_xml.py
formation/handlers/__init__.py
formation/handlers/command.py
formation/handlers/image.py
formation/handlers/layout.py
formation/handlers/misc.py
formation/handlers/scroll.py
formation_studio-0.8.16.dist-info/licenses/LICENSE.txt
hoverset/__init__.py
hoverset/data/__init__.py
hoverset/data/actions.py
hoverset/data/i18n.py
hoverset/data/image.bak
hoverset/data/image.dat
hoverset/data/image.dir
hoverset/data/images.py
hoverset/data/keymap.py
hoverset/data/preferences.py
hoverset/data/utils.py
hoverset/data/locale/zh_CN/LC_MESSAGES/hoverset.mo
hoverset/platform/__init__.py
hoverset/platform/functions.py
hoverset/ui/__init__.py
hoverset/ui/animation.py
hoverset/ui/color.tcl
hoverset/ui/dialogs.py
hoverset/ui/icons.py
hoverset/ui/loaders.py
hoverset/ui/menu.py
hoverset/ui/panels.py
hoverset/ui/pickers.py
hoverset/ui/styles.py
hoverset/ui/widgets.py
hoverset/ui/windows.py
hoverset/ui/themes/default.css
hoverset/ui/themes/light.css
hoverset/util/__init__.py
hoverset/util/color.py
hoverset/util/execution.py
hoverset/util/validators.py
studio/__init__.py
studio/__main__.py
studio/cli.py
studio/context.py
studio/i18n.py
studio/launcher.py
studio/main.py
studio/preferences.py
studio/resource_loader.py
studio/selection.py
studio/updates.py
studio/debugtools/__init__.py
studio/debugtools/__main__.py
studio/debugtools/common.py
studio/debugtools/console.py
studio/debugtools/debugger.py
studio/debugtools/defs.py
studio/debugtools/element_pane.py
studio/debugtools/hook.py
studio/debugtools/layouts.py
studio/debugtools/preferences.py
studio/debugtools/selection.py
studio/debugtools/style_pane.py
studio/external/__init__.py
studio/external/_base.py
studio/external/customtkinter_.py
studio/feature/__init__.py
studio/feature/_base.py
studio/feature/component_tree.py
formation_studio-0.8.16.dist-info/METADATA
formation_studio-0.8.16.dist-info/WHEEL
formation_studio-0.8.16.dist-info/entry_points.txt
formation_studio-0.8.16.dist-info/top_level.txt
formation_studio-0.8.16.dist-info/RECORD
