Metadata-Version: 2.4
Name: formation-studio
Version: 0.8.16
Summary: Simplify GUI development in python
Author-email: Emmanuel Obara <emmanuelobarany@gmail.com>
License: MIT
Project-URL: Documentation, https://formation-studio.readthedocs.io/en/latest/
Project-URL: Issues, https://github.com/ObaraEmmanuel/Formation/issues
Project-URL: Source, https://github.com/ObaraEmmanuel/Formation
Keywords: formation,gui,graphical-user-interface,drag drop,tkinter,hoverset,python
Classifier: Development Status :: 4 - Beta
Classifier: Intended Audience :: Developers
Classifier: Topic :: Software Development :: Build Tools
Classifier: License :: OSI Approved :: MIT License
Classifier: Programming Language :: Python :: 3.9
Classifier: Programming Language :: Python :: 3.10
Classifier: Programming Language :: Python :: 3.11
Classifier: Programming Language :: Python :: 3.12
Classifier: Topic :: Software Development :: Libraries :: Python Modules
Classifier: Topic :: Utilities
Classifier: Topic :: Software Development :: User Interfaces
Classifier: Operating System :: OS Independent
Requires-Python: >=3.9
License-File: LICENSE.txt
Requires-Dist: pyscreenshot; sys_platform != "win32" and sys_platform != "darwin"
Requires-Dist: Pillow
Requires-Dist: platformdirs
Requires-Dist: tkinterdnd2
Provides-Extra: lxml
Requires-Dist: lxml; extra == "lxml"
Provides-Extra: docs
Requires-Dist: Sphinx==4.0.3; extra == "docs"
Requires-Dist: sphinx-rtd-theme==1.0.0; extra == "docs"
Dynamic: license-file
